dstool/__init__.py
dstool/__main__.py
dstool/base.py
dstool/decorators/__init__.py
dstool/decorators/class_utils.py
dstool/decorators/debugger.py
dstool/decorators/measure.py
dstool/parallel/__init__.py
dstool/parallel/parallel_func.py
dstool/plot/__init__.py
dstool/plot/parser.py
dstool/plot/style.py
dstool/tensors/__init__.py
dstool/tensors/safetensors.py
dstool-0.2.0.dist-info/LICENSE
dstool-0.2.0.dist-info/METADATA
dstool-0.2.0.dist-info/WHEEL
dstool-0.2.0.dist-info/entry_points.txt
dstool-0.2.0.dist-info/top_level.txt
dstool-0.2.0.dist-info/RECORD
