Metadata-Version: 2.2
Name: dstool
Version: 0.2.0
Summary: Awesome dstool created by xzyaoi
Home-page: https://github.com/xzyaoi/dstool/
Author: Xiaozhe Yao
License-File: LICENSE
Requires-Dist: joblib
Requires-Dist: plotly
Requires-Dist: rich
Requires-Dist: safetensors
Requires-Dist: typer
Requires-Dist: py7zr
Requires-Dist: zarr
Requires-Dist: cupy-cuda12x
Requires-Dist: scikit-build
Requires-Dist: pytest
Requires-Dist: numcodecs
Requires-Dist: gekko
Requires-Dist: ninja
Provides-Extra: test
Requires-Dist: pytest; extra == "test"
Requires-Dist: coverage; extra == "test"
Requires-Dist: flake8; extra == "test"
Requires-Dist: black; extra == "test"
Requires-Dist: isort; extra == "test"
Requires-Dist: pytest-cov; extra == "test"
Requires-Dist: mypy; extra == "test"
Requires-Dist: gitchangelog; extra == "test"
Requires-Dist: mkdocs; extra == "test"
Dynamic: author
Dynamic: description
Dynamic: description-content-type
Dynamic: home-page
Dynamic: provides-extra
Dynamic: requires-dist
Dynamic: summary
